odoo10_addon_web_menu_navbar_needaction-10.0.1.0.0.99.dev5-py3.8-nspkg.pth
odoo/addons/web_menu_navbar_needaction/README.rst
odoo/addons/web_menu_navbar_needaction/__init__.py
odoo/addons/web_menu_navbar_needaction/__manifest__.py
odoo/addons/web_menu_navbar_needaction/data/ir_config_parameter.xml
odoo/addons/web_menu_navbar_needaction/data/ir_ui_menu.xml
odoo/addons/web_menu_navbar_needaction/i18n/web_menu_navbar_needaction.pot
odoo/addons/web_menu_navbar_needaction/models/__init__.py
odoo/addons/web_menu_navbar_needaction/models/ir_ui_menu.py
odoo/addons/web_menu_navbar_needaction/readme/CONFIGURE.rst
odoo/addons/web_menu_navbar_needaction/readme/CONTRIBUTORS.rst
odoo/addons/web_menu_navbar_needaction/readme/DESCRIPTION.rst
odoo/addons/web_menu_navbar_needaction/static/description/icon.png
odoo/addons/web_menu_navbar_needaction/static/description/index.html
odoo/addons/web_menu_navbar_needaction/static/src/css/web_menu_navbar_needaction.css
odoo/addons/web_menu_navbar_needaction/static/src/js/web_menu_navbar_needaction.js
odoo/addons/web_menu_navbar_needaction/tests/__init__.py
odoo/addons/web_menu_navbar_needaction/tests/test_web_menu_navbar_needaction.py
odoo/addons/web_menu_navbar_needaction/views/ir_ui_menu.xml
odoo/addons/web_menu_navbar_needaction/views/templates.xml
odoo10_addon_web_menu_navbar_needaction-10.0.1.0.0.99.dev5.dist-info/METADATA
odoo10_addon_web_menu_navbar_needaction-10.0.1.0.0.99.dev5.dist-info/WHEEL
odoo10_addon_web_menu_navbar_needaction-10.0.1.0.0.99.dev5.dist-info/namespace_packages.txt
odoo10_addon_web_menu_navbar_needaction-10.0.1.0.0.99.dev5.dist-info/top_level.txt
odoo10_addon_web_menu_navbar_needaction-10.0.1.0.0.99.dev5.dist-info/RECORD
